{
  "libros": [
    {
      "titulo": "Eragon",
      "isbn": "123-LKJ",
      "nPaginas": "320",
      "autor": "Christopher Paolini",
      "digital": true,
      "formatos": {
        "pdf": true,
        "epub": false,
        "dbt": false,
        "tpz": false,
        "mobi": false
      },
      "id": 1
    },
    {
      "titulo": "Harry Potter y la piedra filosofal",
      "isbn": "654-LDN",
      "nPaginas": 223,
      "autor": "J. K. dfweefewf",
      "digital": true,
      "formatos": {
        "pdf": false,
        "epub": false,
        "dbt": true,
        "tpz": false,
        "mobi": false
      },
      "id": 2
    },
    {
      "id": 3,
      "titulo": "El Nombre del Viento",
      "isbn": "861-JFU",
      "nPaginas": "612",
      "autor": "Patrick Rothfuss",
      "digital": false,
      "formatos": {
        "pdf": false,
        "epub": false,
        "dbt": false,
        "tpz": false,
        "mobi": false
      }
    },
    {
      "id": 4,
      "titulo": "eiwughfd",
      "isbn": "0385504209",
      "nPaginas": "91",
      "autor": "wefewf",
      "digital": false,
      "formatos": {
        "pdf": false,
        "epub": false,
        "dbt": false,
        "tpz": false,
        "mobi": false
      }
    },
    {
      "id": 5,
      "titulo": "Luces del Norte",
      "isbn": "783-ICO",
      "nPaginas": 399,
      "autor": "Philip Pullman",
      "digital": true,
      "formatos": {
        "pdf": true,
        "epub": true,
        "dbt": false,
        "tpz": false,
        "mobi": false
      }
    },
    {
      "titulo": "abelardo",
      "isbn": "ohadgnorg",
      "nPaginas": "vewvew",
      "autor": "wefew",
      "digital": true,
      "formatos": {
        "pdf": false,
        "epub": false,
        "dbt": true,
        "tpz": false,
        "mobi": false
      },
      "id": 7
    }
  ]
}